NetHyTech_STT_AI/__init__.py
nethytech_stt_ai-0.1.0.dist-info/METADATA
nethytech_stt_ai-0.1.0.dist-info/WHEEL
nethytech_stt_ai-0.1.0.dist-info/top_level.txt
nethytech_stt_ai-0.1.0.dist-info/RECORD
