Metadata-Version: 2.4
Name: nethytech-stt-ai
Version: 0.1.0
Summary: Speech to Text Python package
Author: Anurag Singh
Author-email: anusin2255@gmail.com
Requires-Python: >=3.8
Requires-Dist: selenium
Requires-Dist: webdriver-manager
Dynamic: author
Dynamic: author-email
Dynamic: description
Dynamic: description-content-type
Dynamic: requires-dist
Dynamic: requires-python
Dynamic: summary
